setup.py
proso/__init__.py
proso/geography/__init__.py
proso/geography/current.py
proso/geography/environment.py
proso/geography/environment_test.py
proso/geography/evaluate.py
proso/geography/metric.py
proso/geography/model.py
proso/geography/model_test.py
proso/geography/optimize.py
proso/geography/prior.py
proso/geography/prior_test.py
proso/geography/recommendation.py
proso/geography/recommendation_test.py
proso/geography/simulator.py
proso_geography_model.egg-info/PKG-INFO
proso_geography_model.egg-info/SOURCES.txt
proso_geography_model.egg-info/dependency_links.txt
proso_geography_model.egg-info/namespace_packages.txt
proso_geography_model.egg-info/requires.txt
proso_geography_model.egg-info/top_level.txt