Metadata-Version: 1.0
Name: proso-geography-model
Version: 1.1.3
Summary: Models library for PROSO Geography project
Home-page: https://github.com/proso/geography-model-libs/
Author: Jan Papousek
Author-email: jan.papousek@gmail.com
License: Gnu GPL v3
Platform: UNKNOWN
